README.md
setup.py
simpleNomo/__init__.py
simpleNomo.egg-info/PKG-INFO
simpleNomo.egg-info/SOURCES.txt
simpleNomo.egg-info/dependency_links.txt
simpleNomo.egg-info/top_level.txt