Metadata-Version: 2.1
Name: simpleNomo
Version: 1.0.0
Summary: Generating nomograms of logistic regression models
Home-page: https://github.com/Hhy096/nomogram
Author: Haoyang Hong
Author-email: haoyanghong@link.cuhk.edu.cn
License: MIT
Keywords: python,nomogram,logistic regression
Platform: UNKNOWN
